fabricka/__init__.py
fabricka/attr_values.py
fabricka/elements.py
fabricka/node.py
fabricka-0.2.0.dist-info/LICENSE
fabricka-0.2.0.dist-info/METADATA
fabricka-0.2.0.dist-info/WHEEL
fabricka-0.2.0.dist-info/RECORD
