Metadata-Version: 2.1
Name: fabricka
Version: 0.2.0
Summary: Build reusable styled HTML components with python.
License: MIT
Author: Said Atta
Author-email: saidattaenp@yahoo.fr
Requires-Python: >=3.11
Classifier: License :: OSI Approved :: MIT License
Classifier: Programming Language :: Python :: 3
Classifier: Programming Language :: Python :: 3.11
Classifier: Programming Language :: Python :: 3.12
